Metadata-Version: 2.1
Name: py-bestmess-client
Version: 0.1.1
Summary: Mess Client
Home-page: UNKNOWN
Author: Pavel Zhirnov
Author-email: pavel@inbox.ru
License: UNKNOWN
Platform: UNKNOWN
Requires-Dist: PyQt5
Requires-Dist: sqlalchemy
Requires-Dist: pycryptodome
Requires-Dist: pycryptodomex
